{
  "collections": {
    "users": {
      "documents": {
        "user1": {
          "name": "John Doe",
          "age": 35,
          "address": {
            "street": "123 Main St",
            "city": "New York",
            "found": "true",
            "postalcode": "nothin",
            "testdate2": "2025-04-11 14:00"
          },
          "testdate2": "2025-04-14 03:00",
          "name2": "nothing burger",
          "was": 0,
          "testarray": [
            "ddsad"
          ]
        },
        "user2": {
          "name": "Jane Doe",
          "age": "281",
          "address": {
            "street": "456 Elm St",
            "city": "Los Angeles",
            "Age": 45
          }
        },
        "test": {
          "array": [
            "2as",
            "'lh;jbj",
            "uvh",
            "testing4"
          ],
          "name": "some name",
          "subDoc": {
            "name": "some other name",
            "value": "some other value"
          },
          "value": "some value"
        },
        "new": {
          "name": "joseph g doe"
        }
      }
    },
    "products": {
      "documents": {
        "product1": {
          "name": "Laptop",
          "price": 1200,
          "stock": 10
        },
        "product2": {
          "name": "Phone",
          "price": 800,
          "stock": 20
        }
      }
    },
    "TVShows": {
      "documents": {
        "StarGateSG1": {
          "Actors": [
            "Richard Dean Anderson",
            "Amanda Tapping",
            "Micheal Shanks"
          ],
          "Locations": [
            "British Columbia, Canada"
          ],
          "Still Active": false
        }
      }
    },
    "new users": {
      "documents": {
        "7cf3dc7c-5a61-4e82-9a85-50ef8ddd3d3c": {
          "sa": "sd"
        },
        "ee537b29-3bf9-45d0-aac1-e77f4e8ab0aa": {
          "fds": "fsdaf"
        },
        "a45fc407-923c-40d7-9578-31abbdc3daa5": {}
      }
    }
  }
}